ev3devlight/__init__.py
ev3devlight/brick.py
ev3devlight/fileio.py
ev3devlight/motors.py
ev3devlight/sensors.py
ev3devlight/virtualhardware.py
ev3devlight-0.1.0.dist-info/DESCRIPTION.rst
ev3devlight-0.1.0.dist-info/METADATA
ev3devlight-0.1.0.dist-info/RECORD
ev3devlight-0.1.0.dist-info/WHEEL
ev3devlight-0.1.0.dist-info/metadata.json
ev3devlight-0.1.0.dist-info/top_level.txt
