Metadata-Version: 2.0
Name: ev3devlight
Version: 0.1.0
Summary: Lightweight ev3dev Micropython and Python library.
Home-page: https://github.com/laurensvalk/ev3devlight
Author: Laurens Valk
Author-email: laurensvalk@gmail.com
License: UNKNOWN
Keywords: lego mindstorms ev3 micropython
Platform: UNKNOWN
Classifier: Development Status :: 3 - Alpha
Classifier: License :: OSI Approved :: MIT License
Classifier: Programming Language :: Python :: 3
Requires-Python: >=3
